.pylintrc
AUTHORS
ChangeLog
LICENSE
README.md
pyproject.toml
requirements-docs.txt
requirements-tests.txt
setup.cfg
setup.py
bin/martini_sour
martini_sour/__init__.py
martini_sour.egg-info/PKG-INFO
martini_sour.egg-info/SOURCES.txt
martini_sour.egg-info/dependency_links.txt
martini_sour.egg-info/not-zip-safe
martini_sour.egg-info/pbr.json
martini_sour.egg-info/requires.txt
martini_sour.egg-info/top_level.txt
martini_sour/data/__init__.py
martini_sour/src/__init__.py
martini_sour/src/analyze.py
martini_sour/src/conv_coords.py
martini_sour/src/conv_itp.py
martini_sour/src/fit_curve.py
martini_sour/src/titrate.py
martini_sour/tests/__init__.py