Metadata-Version: 2.1
Name: martini-sour
Version: 0.0.1.dev19
Summary: UNKNOWN
Home-page: https://github.com/marrink-lab/martini_sour
Author: Fabian Grunewald
Author-email: f.grunewald@rug.nl
License: Apache 2.0
Keywords: Martini coarse-grain titration constant pH
Platform: UNKNOWN
Classifier: Development Status :: 5 - Production/Stable
Classifier: Environment :: Console
Classifier: Intended Audience :: Developers
Classifier: Intended Audience :: Science/Research
Classifier: License :: OSI Approved :: Apache Software License
Classifier: Operating System :: OS Independent
Classifier: Programming Language :: Python :: 3.6
Classifier: Programming Language :: Python :: 3.7
Classifier: Programming Language :: Python :: 3.8
Classifier: Topic :: Scientific/Engineering :: Bio-Informatics
Classifier: Topic :: Scientific/Engineering :: Chemistry
License-File: LICENSE
License-File: AUTHORS
